easy_graph/__init__.py
easy_graph/easy_graph.py
EasyGraph_py-1.4.0.dist-info/LICENSE.txt
EasyGraph_py-1.4.0.dist-info/METADATA
EasyGraph_py-1.4.0.dist-info/WHEEL
EasyGraph_py-1.4.0.dist-info/top_level.txt
EasyGraph_py-1.4.0.dist-info/RECORD
