Metadata-Version: 2.1
Name: EasyGraph-py
Version: 1.4.0
Summary: A simple python module to create all types of graphs.
Home-page: https://github.com/ahmedreza1/EasyGraph
Author: Md Ahmed Reza
Author-email: ahmedreza80@gmail.com
License-File: LICENSE.txt
Requires-Dist: matplotlib
Requires-Dist: pandas
Requires-Dist: seaborn
Requires-Dist: plotly
Requires-Dist: numpy
